multisocketing/__init__.py
multisocketing/clients.py
multisocketing/packets.py
multisocketing/servers.py
multisocketing-1.3.dist-info/LICENSE.md
multisocketing-1.3.dist-info/METADATA
multisocketing-1.3.dist-info/WHEEL
multisocketing-1.3.dist-info/top_level.txt
multisocketing-1.3.dist-info/RECORD
