Metadata-Version: 2.1
Name: multisocketing
Version: 1.3
Summary: A library that makes it easy to make multiplayer
Author: ticks
Author-email: <khaldbedoor@gmail.com>
Keywords: python,multiplayer,server,client,networking,host,sockets
Classifier: Development Status :: 2 - Pre-Alpha
Classifier: Intended Audience :: Developers
Classifier: Programming Language :: Python :: 3
Classifier: Operating System :: Unix
Classifier: Operating System :: MacOS :: MacOS X
Classifier: Operating System :: Microsoft :: Windows
License-File: LICENSE.md
